maper/__init__.py
maper/__main__.py
maper/bibtex.py
maper/create.py
maper/main.py
maper/show.py
maper/util.py
maper-0.1.0.dist-info/METADATA
maper-0.1.0.dist-info/WHEEL
maper-0.1.0.dist-info/entry_points.txt
maper-0.1.0.dist-info/top_level.txt
maper-0.1.0.dist-info/RECORD
