Metadata-Version: 2.1
Name: maper
Version: 0.1.0
Summary: CLI organize PDFs by attaching bibtex metadata
Home-page: https://github.com/chr5tphr/maper
Author: chrstphr
Author-email: maper@j0d.de
License: UNKNOWN
Platform: UNKNOWN
Classifier: Development Status :: 3 - Alpha
Classifier: License :: OSI Approved :: GNU General Public License v3 or later (GPLv3+)
Classifier: Programming Language :: Python :: 3.7
Classifier: Programming Language :: Python :: 3.8
Classifier: Programming Language :: Python :: 3.9
Requires-Python: >=3.7
Requires-Dist: click
Requires-Dist: pikepdf (>=3.0.0b3)
Requires-Dist: requests
